setup.py
status-report
status_report/__init__.py
status_report/base.py
status_report/utils.py
status_report.egg-info/PKG-INFO
status_report.egg-info/SOURCES.txt
status_report.egg-info/dependency_links.txt
status_report.egg-info/not-zip-safe
status_report.egg-info/requires.txt
status_report.egg-info/top_level.txt
status_report/plugins/__init__.py
status_report/plugins/footer.py
status_report/plugins/git.py
status_report/plugins/header.py
status_report/plugins/items.py
status_report/plugins/nitrate.py
status_report/plugins/trac.py