Metadata-Version: 1.1
Name: status-report
Version: 0.3.1
Summary: Status Report - Comfortable CLI Activity Status Reporting
Home-page: https://github.com/psss/status-report
Author: Chris Ward
Author-email: cward@redhat.com
License: GPLv2
Download-URL: https://github.com/psss/status-report/archive/master.zip
Keywords: information,postgresql,tasks,snippets
Platform: UNKNOWN
Classifier: License :: OSI Approved :: GNU General Public License v3 (GPLv3)
Classifier: Natural Language :: English
Classifier: Programming Language :: Python :: 2.7
Classifier: Topic :: Office/Business
Classifier: Topic :: Utilities
Provides: status_report
